relatipy/__init__.py
relatipy/numeric/__init__.py
relatipy/numeric/constants.py
relatipy/numeric/coordinates/__init__.py
relatipy/numeric/coordinates/base.py
relatipy/numeric/coordinates/boyer_lindquist.py
relatipy/numeric/coordinates/cartesian.py
relatipy/numeric/coordinates/spherical.py
relatipy/numeric/geodesic/__init__.py
relatipy/numeric/geodesic/geodesic.py
relatipy/numeric/metrics/__init__.py
relatipy/numeric/metrics/base.py
relatipy/numeric/metrics/kerr_metric.py
relatipy/numeric/metrics/schwarzschild_metric.py
relatipy/symbolic/__init__.py
relatipy/symbolic/coordinates/base.py
relatipy/symbolic/coordinates/boyer_lindquist.py
relatipy/symbolic/coordinates/cylindrical.py
relatipy/symbolic/coordinates/spherical.py
relatipy/symbolic/coordinates/utils.py
relatipy/symbolic/metrics/__init__.py
relatipy/symbolic/metrics/kerr_metric.py
relatipy/visualization/app.py
relatipy-0.1.0.dist-info/METADATA
relatipy-0.1.0.dist-info/WHEEL
relatipy-0.1.0.dist-info/top_level.txt
relatipy-0.1.0.dist-info/RECORD
