Metadata-Version: 2.4
Name: relatipy
Version: 0.1.0
Summary: Numeric and symbolic tools for Kerr black hole geometry
Author: lldddv2
License: MIT
Requires-Python: >=3.10
Requires-Dist: sympy
Requires-Dist: numpy
Requires-Dist: scipy
Requires-Dist: plotly
Requires-Dist: einsteinpy
Provides-Extra: dev
Requires-Dist: black; extra == "dev"
Requires-Dist: flake8; extra == "dev"
Requires-Dist: isort; extra == "dev"
